pspringaws/__init__.py
pspringaws/defaultvars.py
pspringaws/dynamodb.py
pspringaws/dynamodbconfigprovider.py
pspringaws/lambdaexceptions.py
pspringaws/lambdahandler.py
pspringaws/pspringaws.py
pspringaws/realtimedynamodb.py
pspringaws/realtimedynamodbconfigprovider.py
pspringaws/realtimes3.py
pspringaws/realtimes3configprovider.py
pspringaws/realtimesecretsmngrconfigprovider.py
pspringaws/s3configprovider.py
pspringaws/scheduleds3configprovider.py
pspringaws/scheduledsecretsmngrconfigprovider.py
pspringaws/secretsmngr.py
pspringaws/secretsmngrconfigprovider.py
pspring_aws-0.0.44.dist-info/LICENSE
pspring_aws-0.0.44.dist-info/METADATA
pspring_aws-0.0.44.dist-info/WHEEL
pspring_aws-0.0.44.dist-info/top_level.txt
pspring_aws-0.0.44.dist-info/RECORD
