Metadata-Version: 2.1
Name: pspring-aws
Version: 0.0.44
Summary: A framework to do a better development.
Home-page: https://github.com/vasudevan-palani/pspring-aws
Author: Vasudevan Palani
Author-email: vasudevan.palani@gmail.com
License: TBD
Platform: UNKNOWN
Requires-Dist: boto3 (>1.9)
Requires-Dist: pspring (>=0.0.1)
Requires-Dist: realtime-aws-secretsmngr (>=0.0.3)
Requires-Dist: PyYAML (>=5.3)
Requires-Dist: moto
